{"am_pm_abbreviated":["午前","午後"],"date_format_full":"y年M月d日EEEE","date_format_long":"y年M月d日","date_format_medium":"y/MM/dd","date_format_short":"y/MM/dd","datetime_format":"{1} {0}","datetime_format_full":"y年M月d日EEEE H時mm分ss秒 zzzz","datetime_format_long":"y年M月d日 H:mm:ss z","datetime_format_medium":"y/MM/dd H:mm:ss","datetime_format_short":"y/MM/dd H:mm","day_format_abbreviated":["月","火","水","木","金","土","日"],"day_format_narrow":["月","火","水","木","金","土","日"],"day_format_wide":["月曜日","火曜日","水曜日","木曜日","金曜日","土曜日","日曜日"],"day_stand_alone_abbreviated":["月","火","水","木","金","土","日"],"day_stand_alone_narrow":["月","火","水","木","金","土","日"],"day_stand_alone_wide":["月曜日","火曜日","水曜日","木曜日","金曜日","土曜日","日曜日"],"first_day_of_week":1,"month_format_abbreviated":["1月","2月","3月","4月","5月","6月","7月","8月","9月","10月","11月","12月"],"month_format_narrow":[1,2,3,4,5,6,7,8,9,10,11,12],"month_format_wide":["1月","2月","3月","4月","5月","6月","7月","8月","9月","10月","11月","12月"],"month_stand_alone_abbreviated":["1月","2月","3月","4月","5月","6月","7月","8月","9月","10月","11月","12月"],"month_stand_alone_narrow":[1,2,3,4,5,6,7,8,9,10,11,12],"month_stand_alone_wide":["1月","2月","3月","4月","5月","6月","7月","8月","9月","10月","11月","12月"],"prefers_24_hour_time":1,"time_format_full":"H時mm分ss秒 zzzz","time_format_long":"H:mm:ss z","time_format_medium":"H:mm:ss","time_format_short":"H:mm"}